descriptorlib/__init__.py
descriptorlib/run_tests.py
descriptorlib/monomer/MonomerPropertyDescriptor.py
descriptorlib/monomer/__init__.py
descriptorlib/monomer/base.py
descriptorlib/monomer/libException/MonomerPropertyException.py
descriptorlib/monomer/libException/SerializationError.py
descriptorlib/monomer/libException/__init__.py
descriptorlib/monomer/libException/libError.py
descriptorlib/monomer/utils/__init__.py
descriptorlib/monomer/utils/utils.py
descriptorlib/tests/__init__.py
descriptorlib/tests/test_Monomer.py
descriptorlib/tests/test_libException.py
descriptorlib-0.1.4.dist-info/LICENSE
descriptorlib-0.1.4.dist-info/METADATA
descriptorlib-0.1.4.dist-info/WHEEL
descriptorlib-0.1.4.dist-info/top_level.txt
descriptorlib-0.1.4.dist-info/RECORD
