Metadata-Version: 2.1
Name: descriptorlib
Version: 0.1.4
Summary: Descriptorlib is a Python library that provides a series of powerful descriptors for enhancing the attribute functionality of Python classes.
Author-email: 解文 <2965312076@qq.com>
License:                   GNU LESSER GENERAL PUBLIC LICENSE
Project-URL: Bug Reports, https://github.com/nostalgiatan/Descriptorlib/issues
Project-URL: Source, https://github.com/nostalgiatan/Descriptorlib/
Project-URL: Documentation, https://github.com/nostalgiatan/Descriptorlib/wiki
Keywords: descriptor,function,描述符,属性描述,Python descriptors,class attributes,property decorators
Classifier: Programming Language :: Python :: 3
Classifier: License :: OSI Approved :: GNU Lesser General Public License v3 (LGPLv3)
Classifier: Operating System :: OS Independent
Requires-Python: >=3.8
License-File: LICENSE
Provides-Extra: test
Requires-Dist: pytest>=6.0.0; extra == "test"
Requires-Dist: coverage>=5.0; extra == "test"
